myproxy/.gitignore
myproxy/__init__.py
myproxy/client/LICENSE
myproxy/client/__init__.py
myproxy/client/script.py
myproxy/client/test/.gitignore
myproxy/client/test/7e15277f.0
myproxy/client/test/7e15277f.signing_policy
myproxy/client/test/README
myproxy/client/test/Vagrantfile
myproxy/client/test/__init__.py
myproxy/client/test/expired.crt
myproxy/client/test/localhost.crt
myproxy/client/test/localhost.key
myproxy/client/test/myProxyClient.cfg
myproxy/client/test/myProxyClientTest.cfg
myproxy/client/test/myproxy-server.config
myproxy/client/test/openssl.conf
myproxy/client/test/test_myproxyclient.py
myproxy/client/test/testuser.crt
myproxy/client/test/testuser.csr
myproxy/client/test/testuser.key
myproxy/client/utils/__init__.py
myproxy/client/utils/openssl.py
myproxyclient-2.2.0.dist-info/METADATA
myproxyclient-2.2.0.dist-info/WHEEL
myproxyclient-2.2.0.dist-info/entry_points.txt
myproxyclient-2.2.0.dist-info/top_level.txt
myproxyclient-2.2.0.dist-info/RECORD
